setup.py
python_streamtools.egg-info/PKG-INFO
python_streamtools.egg-info/SOURCES.txt
python_streamtools.egg-info/dependency_links.txt
python_streamtools.egg-info/namespace_packages.txt
python_streamtools.egg-info/not-zip-safe
python_streamtools.egg-info/requires.txt
python_streamtools.egg-info/top_level.txt
streamtools/__init__.py
streamtools/client.py
streamtools/models.py
streamtools/settings.py
streamtools/util.py