Metadata-Version: 1.1
Name: python-streamtools
Version: 0.1.0
Summary: A python wrapper for streamtools: http://nytlabs.github.io/streamtools
Home-page: http://github.com/abelsonlive/python-streamtools
Author: Brian Abelson
Author-email: brian@newslynx.org
License: MIT
Platform: UNKNOWN
Classifier: Development Status :: 3 - Alpha
Classifier: Intended Audience :: Developers
Classifier: License :: OSI Approved :: MIT License
Classifier: Operating System :: OS Independent
Classifier: Programming Language :: Python
